testerino/__init__.py
testerino/add.py
testerino-0.1.0.dist-info/WHEEL
testerino-0.1.0.dist-info/METADATA
testerino-0.1.0.dist-info/RECORD
