Metadata-Version: 2.1
Name: testerino
Version: 0.1.0
Summary: 
Author: Michael Watson
Author-email: test@gmail.com
Requires-Python: >=3.9,<4.0
Classifier: Programming Language :: Python :: 3
Classifier: Programming Language :: Python :: 3.10
Classifier: Programming Language :: Python :: 3.9
Requires-Dist: requests (>=2.27.1,<3.0.0)
